LICENSE
README.md
setup.cfg
setup.py
txtv/__init__.py
txtv/__main__.py
txtv/config.py
txtv/listing.py
txtv/test.py
txtv/txtv.py
txtv/util.py
txtv.egg-info/PKG-INFO
txtv.egg-info/SOURCES.txt
txtv.egg-info/dependency_links.txt
txtv.egg-info/entry_points.txt
txtv.egg-info/requires.txt
txtv.egg-info/top_level.txt