Metadata-Version: 2.1
Name: txtv
Version: 2.0.0
Summary: CLI for reading swedish text-tv
Home-page: https://github.com/voidcase/txtv
Author: Isak Lindhé
Author-email: isak.e.lindhe@gmail.com
License: GPLv3+
Download-URL: https://github.com/voidcase/txtv/archive/v2.0.0.tar.gz
Platform: UNKNOWN
Classifier: Programming Language :: Python :: 3
Classifier: Programming Language :: Python :: 3.6
Classifier: Programming Language :: Python :: 3.7
Classifier: Environment :: Console
Classifier: License :: OSI Approved :: GNU General Public License v3 or later (GPLv3+)
Classifier: Operating System :: POSIX
Classifier: Operating System :: MacOS
Classifier: Topic :: Internet :: WWW/HTTP :: Dynamic Content :: News/Diary
Classifier: Natural Language :: Swedish
Requires-Python: >=3.6
License-File: LICENSE
